omg/__init__.py
omg/account.py
omg/address.py
omg/api.py
omg/client.py
omg/constants.py
omg/dns.py
omg/email.py
omg/errors.py
omg/misc.py
omg/now_page.py
omg/pastebin.py
omg/pics.py
omg/purl.py
omg/service.py
omg/statuslog.py
omg/themes.py
omg/utils.py
omg/web.py
omg/weblog.py
omg_lol-1.0.dist-info/METADATA
omg_lol-1.0.dist-info/WHEEL
omg_lol-1.0.dist-info/licenses/LICENSE
omg_lol-1.0.dist-info/RECORD
